fucknuker/__init__.py
fucknuker/main.py
fucknukeer-0.1.3.dist-info/METADATA
fucknukeer-0.1.3.dist-info/WHEEL
fucknukeer-0.1.3.dist-info/entry_points.txt
fucknukeer-0.1.3.dist-info/top_level.txt
fucknukeer-0.1.3.dist-info/RECORD
